jaclang_jaseci/__init__.py
jaclang_jaseci/core/__init__.py
jaclang_jaseci/core/architype.py
jaclang_jaseci/core/context.py
jaclang_jaseci/core/memory.py
jaclang_jaseci/jaseci/__init__.py
jaclang_jaseci/jaseci/datasources/__init__.py
jaclang_jaseci/jaseci/datasources/collection.py
jaclang_jaseci/jaseci/datasources/redis.py
jaclang_jaseci/jaseci/dtos/__init__.py
jaclang_jaseci/jaseci/dtos/sso.py
jaclang_jaseci/jaseci/dtos/user.py
jaclang_jaseci/jaseci/models/__init__.py
jaclang_jaseci/jaseci/models/user.py
jaclang_jaseci/jaseci/routers/__init__.py
jaclang_jaseci/jaseci/routers/healthz.py
jaclang_jaseci/jaseci/routers/sso.py
jaclang_jaseci/jaseci/routers/user.py
jaclang_jaseci/jaseci/security/__init__.py
jaclang_jaseci/jaseci/sso/__init__.py
jaclang_jaseci/jaseci/sso/apple.py
jaclang_jaseci/jaseci/sso/google.py
jaclang_jaseci/jaseci/utils/__init__.py
jaclang_jaseci/jaseci/utils/mail.py
jaclang_jaseci/plugin/__init__.py
jaclang_jaseci/plugin/jaseci.py
jaclang_jaseci/tests/__init__.py
jaclang_jaseci/tests/test_simple_graph.py
jaclang_jaseci-0.2.0.dist-info/LICENSE
jaclang_jaseci-0.2.0.dist-info/METADATA
jaclang_jaseci-0.2.0.dist-info/WHEEL
jaclang_jaseci-0.2.0.dist-info/entry_points.txt
jaclang_jaseci-0.2.0.dist-info/top_level.txt
jaclang_jaseci-0.2.0.dist-info/RECORD
