Metadata-Version: 2.1
Name: jaclang-jaseci
Version: 0.2.0
Home-page: https://github.com/Jaseci-Labs/jaclang
Author: Jason Mars
Author-email: jason@jaseci.org
License-File: LICENSE
Requires-Dist: jaclang==0.7.15
Requires-Dist: fastapi==0.111.0
Requires-Dist: pydantic==2.8.2
Requires-Dist: pymongo==4.8.0
Requires-Dist: motor==3.5.0
Requires-Dist: motor-types==1.0.0b4
Requires-Dist: python-dotenv==1.0.1
Requires-Dist: uvicorn==0.30.1
Requires-Dist: pyjwt[crypto]==2.8.0
Requires-Dist: passlib==1.7.4
Requires-Dist: types-passlib==1.7.7.20240327
Requires-Dist: email-validator==2.2.0
Requires-Dist: orjson==3.10.6
Requires-Dist: redis==5.0.7
Requires-Dist: types-redis==4.6.0.20240425
Requires-Dist: python-multipart==0.0.9
Requires-Dist: httpx==0.27.0
Requires-Dist: sendgrid==6.11.0
Requires-Dist: fastapi-sso==0.15.0
Requires-Dist: google-auth==2.32.0
